{
  "generated_at": "2026-07-02T08:49:48.325710+00:00",
  "commit": "807e1df9",
  "diagnostic_logd": [
    "diagnostic\\build-807e1df9-part001.logd",
    "diagnostic\\build-807e1df9-part002.logd",
    "diagnostic\\build-807e1df9-part003.logd",
    "diagnostic\\build-807e1df9-part004.logd",
    "diagnostic\\build-807e1df9-part005.logd",
    "diagnostic\\build-807e1df9-part006.logd"
  ],
  "diagnostic_logd_error": null,
  "message_blocker": null,
  "chunked": true,
  "chunk_size_bytes": 41943040,
  "password": "0926ef10979810a4cd74",
  "decrypt_command": "encryptly unpack diagnostic\\build-807e1df9.logd <outdir> --password 0926ef10979810a4cd74",
  "total_modules": 10,
  "passed": 1,
  "failed": 9,
  "modules": [
    {
      "name": "backend",
      "status": "FAIL",
      "elapsed_seconds": 0,
      "artifact": null,
      "output": "Command not found: [WinError 2] \u7cfb\u7edf\u627e\u4e0d\u5230\u6307\u5b9a\u7684\u6587\u4ef6\u3002"
    },
    {
      "name": "frontend",
      "status": "FAIL",
      "elapsed_seconds": 0,
      "artifact": null,
      "output": "Command not found: [WinError 2] \u7cfb\u7edf\u627e\u4e0d\u5230\u6307\u5b9a\u7684\u6587\u4ef6\u3002"
    },
    {
      "name": "market",
      "status": "FAIL",
      "elapsed_seconds": 0,
      "artifact": null,
      "output": "Command not found: [WinError 2] \u7cfb\u7edf\u627e\u4e0d\u5230\u6307\u5b9a\u7684\u6587\u4ef6\u3002"
    },
    {
      "name": "frailbox",
      "status": "FAIL",
      "elapsed_seconds": 0,
      "artifact": null,
      "output": "Command not found: [WinError 2] \u7cfb\u7edf\u627e\u4e0d\u5230\u6307\u5b9a\u7684\u6587\u4ef6\u3002"
    },
    {
      "name": "engine",
      "status": "FAIL",
      "elapsed_seconds": 0,
      "artifact": null,
      "output": "Command not found: [WinError 2] \u7cfb\u7edf\u627e\u4e0d\u5230\u6307\u5b9a\u7684\u6587\u4ef6\u3002"
    },
    {
      "name": "compliance",
      "status": "PASS",
      "elapsed_seconds": 0.711,
      "artifact": "D:\\hermes-data\\bounty-hunter\\worktrees\\TentOfTrials\\compliance\\build",
      "output": ""
    },
    {
      "name": "v2-market-stream",
      "status": "FAIL",
      "elapsed_seconds": 0,
      "artifact": null,
      "output": "Command not found: [WinError 2] \u7cfb\u7edf\u627e\u4e0d\u5230\u6307\u5b9a\u7684\u6587\u4ef6\u3002"
    },
    {
      "name": "nfc-scanner",
      "status": "FAIL",
      "elapsed_seconds": 0,
      "artifact": null,
      "output": "Command not found: [WinError 2] \u7cfb\u7edf\u627e\u4e0d\u5230\u6307\u5b9a\u7684\u6587\u4ef6\u3002"
    },
    {
      "name": "openapi-haskell",
      "status": "FAIL",
      "elapsed_seconds": 0,
      "artifact": null,
      "output": "Command not found: [WinError 2] \u7cfb\u7edf\u627e\u4e0d\u5230\u6307\u5b9a\u7684\u6587\u4ef6\u3002"
    },
    {
      "name": "openapi-tools",
      "status": "FAIL",
      "elapsed_seconds": 0,
      "artifact": null,
      "output": "Command not found: [WinError 2] \u7cfb\u7edf\u627e\u4e0d\u5230\u6307\u5b9a\u7684\u6587\u4ef6\u3002"
    }
  ],
  "pr_note": "Include the encrypted diagnostic logd artifact(s): diagnostic\\build-807e1df9-part001.logd, diagnostic\\build-807e1df9-part002.logd, diagnostic\\build-807e1df9-part003.logd, diagnostic\\build-807e1df9-part004.logd, diagnostic\\build-807e1df9-part005.logd, diagnostic\\build-807e1df9-part006.logd. The encrypted .logd is the required diagnostic content for PR review; this JSON file is metadata. Maintainers may ask you to remove these diagnostic artifacts before merging."
}
